{"buildingList":[{"_id":"Building:2d4ad281-0ffc-4505-9d68-c5bec89d87ee","position":{"x":34.5,"y":5.0,"z":56.5},"rotation":{"x":0.0,"y":0.0,"z":0.0,"w":1.0},"selectedPrefabId":26686,"tag":"Placed","placeablePrice":1500,"reachable":true,"capacity":15,"defaultCapacity":15,"visitorsIds":["Visitor:5f3add7e-7c85-4d36-b9f8-b90abe569a3b","Visitor:b64fd5db-4221-4930-a31e-0706ab89a611","Visitor:0a791c73-5905-4ff4-92a6-ab221135a0d5"],"x":2,"z":1,"startingGridIndex":{"x":2.0,"y":0.0,"z":24.0},"purchasableItemInstancesData":[{"itemName":"Burger","currentPrice":15.0},{"itemName":"Fries","currentPrice":10.0},{"itemName":"Water","currentPrice":5.0}]},{"_id":"Building:ad5ef322-25dc-458e-a72e-55a552979ab2","position":{"x":38.5,"y":5.0,"z":43.5},"rotation":{"x":2.52817732E-12,"y":1.0,"z":0.0,"w":1.24261712E-13},"selectedPrefabId":26688,"tag":"Placed","placeablePrice":1000,"reachable":true,"capacity":10,"defaultCapacity":10,"visitorsIds":["Visitor:06b78165-cfbc-403a-bf1f-967b9b2c3abd","Visitor:774ee51e-0543-4e50-a7ff-e71bbf18a3b7"],"x":-1,"z":-1,"startingGridIndex":{"x":6.0,"y":0.0,"z":11.0},"purchasableItemInstancesData":[{"itemName":"Coffee","currentPrice":5.0},{"itemName":"Hot Chocolate","currentPrice":8.0},{"itemName":"Water","currentPrice":5.0}]}],"itemsBought":5}