{"fences":[{"_id":"Fence:0923a847-ac19-4d4e-ac73-e04003c7452f","position":{"x":40.5,"y":3.5,"z":58.5},"selectedPrefabId":28594,"rotation":{"x":0.0,"y":0.0,"z":0.0,"w":1.0},"placeablePrice":180,"tag":"Placed Fence","timesRotated":0},{"_id":"Fence:a51b808f-11da-47c9-a275-a4848df3bc2f","position":{"x":41.5,"y":3.5,"z":58.5},"selectedPrefabId":28594,"rotation":{"x":0.0,"y":0.0,"z":0.0,"w":1.0},"placeablePrice":180,"tag":"Placed Fence","timesRotated":0},{"_id":"Fence:ddf5fde1-9fbc-4529-b973-813e5d16b0c0","position":{"x":42.5,"y":3.5,"z":58.5},"selectedPrefabId":28594,"rotation":{"x":0.0,"y":0.0,"z":0.0,"w":1.0},"placeablePrice":180,"tag":"Placed Fence","timesRotated":0},{"_id":"Fence:eec45b73-5ab4-4ff7-972d-f7f409fa4a91","position":{"x":43.5,"y":3.5,"z":57.5},"selectedPrefabId":28594,"rotation":{"x":0.0,"y":0.7071068286895752,"z":0.0,"w":0.7071068286895752},"placeablePrice":180,"tag":"Placed Fence","timesRotated":1},{"_id":"Fence:f88dbc8a-7470-443a-8218-c8985c88953a","position":{"x":42.5,"y":3.5,"z":58.5},"selectedPrefabId":28594,"rotation":{"x":0.0,"y":0.7071068286895752,"z":0.0,"w":0.7071068286895752},"placeablePrice":180,"tag":"Placed Fence","timesRotated":1},{"_id":"Fence:2df6b35f-32df-41c8-9117-84f08a590c69","position":{"x":42.5,"y":3.5,"z":57.5},"selectedPrefabId":28594,"rotation":{"x":0.0,"y":0.7071068286895752,"z":0.0,"w":0.7071068286895752},"placeablePrice":180,"tag":"Placed Fence","timesRotated":1},{"_id":"Fence:1b8e4603-9f81-4b6c-82de-e2c289c4e141","position":{"x":42.5,"y":3.5,"z":56.5},"selectedPrefabId":28594,"rotation":{"x":0.0,"y":0.7071068286895752,"z":0.0,"w":0.7071068286895752},"placeablePrice":180,"tag":"Placed Fence","timesRotated":1},{"_id":"Fence:ec385d15-a56e-4358-a626-c1c4acdeaa12","position":{"x":42.5,"y":3.5,"z":56.5},"selectedPrefabId":28594,"rotation":{"x":0.0,"y":1.0,"z":0.0,"w":0.0},"placeablePrice":180,"tag":"Placed Fence","timesRotated":2},{"_id":"Fence:8bc8ac53-e0bb-45c7-867c-4823fcc5ba14","position":{"x":40.5,"y":3.5,"z":56.5},"selectedPrefabId":28594,"rotation":{"x":0.0,"y":1.0,"z":0.0,"w":0.0},"placeablePrice":180,"tag":"Placed Fence","timesRotated":2},{"_id":"Fence:56d21d68-4312-4c8e-86b0-fb8eef3de57d","position":{"x":41.5,"y":3.5,"z":56.5},"selectedPrefabId":28594,"rotation":{"x":0.0,"y":1.0,"z":0.0,"w":0.0},"placeablePrice":180,"tag":"Placed Fence","timesRotated":2},{"_id":"Fence:c4225cbe-81db-48b8-8f47-8840619230a3","position":{"x":40.5,"y":3.5,"z":56.5},"selectedPrefabId":28594,"rotation":{"x":0.0,"y":0.7071068286895752,"z":0.0,"w":-0.7071068286895752},"placeablePrice":180,"tag":"Placed Fence","timesRotated":3},{"_id":"Fence:04f7d5ff-49d4-4800-a78c-8c4467a68992","position":{"x":40.5,"y":3.5,"z":57.5},"selectedPrefabId":28594,"rotation":{"x":0.0,"y":0.7071068286895752,"z":0.0,"w":-0.7071068286895752},"placeablePrice":180,"tag":"Placed Fence","timesRotated":3}]}