{"pathList":[{"_id":"Path:78dddbb1-3e6b-4355-8d14-f23c4410e18c","position":{"x":37.5,"y":3.5,"z":53.5},"selectedPrefabId":30252,"placeablePrice":30,"tag":"Placed Path","rotation":{"x":0.0,"y":0.0,"z":0.0,"w":1.0}},{"_id":"Path:9037063a-1a78-41a6-8794-02249dbdd194","position":{"x":38.5,"y":3.25,"z":53.5},"selectedPrefabId":30260,"placeablePrice":30,"tag":"Placed Path","rotation":{"x":0.0,"y":1.0,"z":0.0,"w":-4.371139E-08}},{"_id":"Path:7fb93177-32e2-44a2-a2c6-82a88bf0061b","position":{"x":39.5,"y":3.0,"z":53.5},"selectedPrefabId":30252,"placeablePrice":30,"tag":"Placed Path","rotation":{"x":0.0,"y":0.0,"z":0.0,"w":1.0}},{"_id":"Path:c3b3f412-31f6-4772-bdd4-d64d3248f627","position":{"x":40.5,"y":3.0,"z":53.5},"selectedPrefabId":30252,"placeablePrice":30,"tag":"Placed Path","rotation":{"x":0.0,"y":0.0,"z":0.0,"w":1.0}},{"_id":"Path:d8c65b3e-7ff2-42ee-9db7-5e7bb74e07c4","position":{"x":41.5,"y":3.0,"z":53.5},"selectedPrefabId":30252,"placeablePrice":30,"tag":"Placed Path","rotation":{"x":0.0,"y":0.0,"z":0.0,"w":1.0}},{"_id":"Path:b97d7eab-4998-4951-98bd-f0a541ac8b88","position":{"x":42.5,"y":3.0,"z":53.5},"selectedPrefabId":30252,"placeablePrice":30,"tag":"Placed Path","rotation":{"x":0.0,"y":0.0,"z":0.0,"w":1.0}},{"_id":"Path:10946d4f-b2fd-4c78-a446-1ee5506a6f8d","position":{"x":43.5,"y":3.0,"z":53.5},"selectedPrefabId":30252,"placeablePrice":30,"tag":"Placed Path","rotation":{"x":0.0,"y":0.0,"z":0.0,"w":1.0}},{"_id":"Path:5b586736-4286-49bf-a558-36b15f534432","position":{"x":44.5,"y":3.0,"z":53.5},"selectedPrefabId":30252,"placeablePrice":30,"tag":"Placed Path","rotation":{"x":0.0,"y":0.0,"z":0.0,"w":1.0}},{"_id":"Path:de3679e3-4207-4a6e-896a-4107a945c02e","position":{"x":45.5,"y":3.0,"z":53.5},"selectedPrefabId":30252,"placeablePrice":30,"tag":"Placed Path","rotation":{"x":0.0,"y":0.0,"z":0.0,"w":1.0}},{"_id":"Path:26103e8e-ce31-49ac-974d-4a150ce59417","position":{"x":45.5,"y":3.0,"z":54.5},"selectedPrefabId":30252,"placeablePrice":30,"tag":"Placed Path","rotation":{"x":0.0,"y":0.0,"z":0.0,"w":1.0}},{"_id":"Path:d41a3175-6a66-442f-957d-42c3fd3a00be","position":{"x":45.5,"y":3.0,"z":55.5},"selectedPrefabId":30252,"placeablePrice":30,"tag":"Placed Path","rotation":{"x":0.0,"y":0.0,"z":0.0,"w":1.0}},{"_id":"Path:54c84002-9dcd-4610-987a-79a66edbfbd9","position":{"x":45.5,"y":3.0,"z":56.5},"selectedPrefabId":30252,"placeablePrice":30,"tag":"Placed Path","rotation":{"x":0.0,"y":0.0,"z":0.0,"w":1.0}},{"_id":"Path:eb4598a9-43f9-4bb5-a47b-34d4bcbab374","position":{"x":45.5,"y":3.0,"z":57.5},"selectedPrefabId":30252,"placeablePrice":30,"tag":"Placed Path","rotation":{"x":0.0,"y":0.0,"z":0.0,"w":1.0}},{"_id":"Path:ece13a55-e6e2-4892-9fda-dd544556665c","position":{"x":45.5,"y":3.0,"z":58.5},"selectedPrefabId":30252,"placeablePrice":30,"tag":"Placed Path","rotation":{"x":0.0,"y":0.0,"z":0.0,"w":1.0}},{"_id":"Path:46acac7a-da47-45a9-9a47-73290311f1c9","position":{"x":45.5,"y":3.0,"z":59.5},"selectedPrefabId":30252,"placeablePrice":30,"tag":"Placed Path","rotation":{"x":0.0,"y":0.0,"z":0.0,"w":1.0}}]}